[{"ID":139,"技能":"猛烈撞击","等级":0,"系别":"[普]","类型":"[物理攻击]","威力":35,"PP值":35,"命中率":"94%","优先度":8,"信息介绍":"给对手造成一定伤害"},{"ID":156,"技能":"愤怒还击","等级":0,"系别":"[恶]","类型":"[物理攻击]","威力":50,"PP值":10,"命中率":"100%","优先度":8,"信息介绍":"给对手造成一定伤害, 若该回合受到伤害, 造成伤害加倍"},{"ID":50,"技能":"控制意念","等级":0,"系别":"[萌]","类型":"[魔法攻击]","威力":50,"PP值":25,"命中率":"100%","优先度":8,"信息介绍":"给对手造成一定伤害, 较低机率让对手混乱"},{"ID":16,"技能":"能量弹","等级":11,"系别":"[恶]","类型":"[物理攻击]","威力":50,"PP值":10,"命中率":"100%","优先度":8,"信息介绍":"给对手造成一定伤害"},{"ID":117,"技能":"近身拍打","等级":15,"系别":"[恶]","类型":"[物理攻击]","威力":60,"PP值":25,"命中率":"100%","优先度":8,"信息介绍":"给对手造成较高伤害, 一定机率让对手恐惧"},{"ID":80,"技能":"混乱电击","等级":19,"系别":"[萌]","类型":"[魔法攻击]","威力":65,"PP值":20,"命中率":"100%","优先度":8,"信息介绍":"给对手造成较高伤害, 较低机率让对方进入到混乱状态"},{"ID":166,"技能":"狂暴拳法","等级":23,"系别":"[恶]","类型":"[物理攻击]","威力":70,"PP值":15,"命中率":"100%","优先度":8,"信息介绍":"给对手造成较高伤害, 本回合提高暴击率"},{"ID":333,"技能":"反射护盾","等级":27,"系别":"[萌]","类型":"[变化攻击]","威力":0,"PP值":20,"命中率":"100%","优先度":8,"信息介绍":"10回合内, 己方受到的物理伤害减半"},{"ID":39,"技能":"献祭之焰","等级":31,"系别":"[恶]","类型":"[变化攻击]","威力":0,"PP值":10,"命中率":"100%","优先度":8,"信息介绍":"令对手攻击和魔攻等级下降, 使用后自身HP变为零"},{"ID":206,"技能":"恐惧头槌","等级":35,"系别":"[萌]","类型":"[物理攻击]","威力":80,"PP值":15,"命中率":"89%","优先度":8,"信息介绍":"给对手造成较高伤害, 较低机率让对手恐惧"},{"ID":235,"技能":"恐吓","等级":39,"系别":"[恶]","类型":"[魔法攻击]","威力":90,"PP值":15,"命中率":"90%","优先度":8,"信息介绍":"给对手造成较高伤害, 较高机率让对手恐惧"},{"ID":231,"技能":"黑暗诅咒","等级":43,"系别":"[恶]","类型":"[魔法攻击]","威力":80,"PP值":15,"命中率":"100%","优先度":8,"信息介绍":"给对手造成较高伤害, 较低机率让对手恐惧"},{"ID":327,"技能":"恶魔契约","等级":47,"系别":"[恶]","类型":"[变化攻击]","威力":0,"PP值":5,"命中率":"100%","优先度":8,"信息介绍":"回复自身HP, 每回合回复1/16,持续16回合"},{"ID":191,"技能":"反制一击","等级":51,"系别":"[恶]","类型":"[物理攻击]","威力":90,"PP值":10,"命中率":"65%","优先度":8,"信息介绍":"给对手造成较高伤害, 本回合如果后发动, 则造成2倍威力伤害"}]
